{
  "id": 100500,
  "arrival_application": 0,
  "receiver_id": 0,
  "loaders": [0],
  "unload_cost": 0,
  "unload_place": 0,
  "materials": [
    {
      "id": 0,
      "amount": 52,
      "amount_expected": 10,
      "name": "Штукатурка",
      "measurement_unit": "кг"
    },
    {
      "id": 1,
      "amount": 120,
      "amount_expected": 130,
      "name": "Мешочки",
      "measurement_unit": "шт"
    }
  ],
  "tools": [
    {
      "id": 1,
      "amount": 10,
      "amount_expected": 15,
      "name": "Пепяка",
      "measurement_unit": "мм"
    },
    {
      "id": 92,
      "amount": 10,
      "amount_expected": 8,
      "name": "Шячлы",
      "measurement_unit": "см"
    }
  ],
  "finished_at": "2019-09-30T12:47:42Z",
  "deleted_at": "2019-09-30T12:47:42Z",
  "created_at": "2019-09-30T12:47:42Z",
  "updated_at": "2019-09-30T12:47:42Z"
}
